getarticle/__init__.py
getarticle/cli.py
getarticle/getarticle.py
getarticle_dev-0.0.7.dist-info/LICENSE
getarticle_dev-0.0.7.dist-info/METADATA
getarticle_dev-0.0.7.dist-info/WHEEL
getarticle_dev-0.0.7.dist-info/entry_points.txt
getarticle_dev-0.0.7.dist-info/top_level.txt
getarticle_dev-0.0.7.dist-info/RECORD
