Metadata-Version: 2.1
Name: getarticle-dev
Version: 0.0.7
Summary: A package based on SciHub and Google             Scholar that can download articles given DOI,             website address or keywords.
Home-page: https://github.com/HTian1997/getarticle
Author: Hao Tian
Author-email: htian1997@gmail.com
License: MIT
Platform: UNKNOWN
Requires-Dist: requests
Requires-Dist: argparse
Requires-Dist: appscript ; platform_system == "Darwin"
